giant/__init__.py
giant/giant_steps.py
giant-1.1.4.dist-info/LICENSE
giant-1.1.4.dist-info/METADATA
giant-1.1.4.dist-info/WHEEL
giant-1.1.4.dist-info/top_level.txt
giant-1.1.4.dist-info/RECORD
