Metadata-Version: 2.1
Name: giant
Version: 1.1.4
Summary: Giant challengeFor linux installations run this before installing:     conda uninstall PortAudio     sudo apt-get install portaudio19-dev.Need more help? Check the dependencies websites
Home-page: UNKNOWN
Author: GSCap
Author-email: sistemas@gscap.com.br
License: UNKNOWN
Platform: UNKNOWN
Requires-Python: >=3.6
Requires-Dist: pycrypto
Requires-Dist: pysine
